{
  "categories": [],
  "content": "Best ways to start saving",
  "created": "2023-06-28T08:49:28.846Z",
  "guideType": "onboarding",
  "key": "how-to-start-saving-credit-union-academy",
  "name": "How to Start Saving",
  "publishStatus": "Live",
  "showIncorrectOnCompletion": true,
  "steps": [
    {
      "content": "Starting to save money at a young age is crucial for building wealth and securing a comfortable future. Even though retirement may seem far off, saving for it as early as possible will ensure that you have enough money to support yourself during your retirement years. The best time to start saving is when you start earning money for yourself, whether it's from chores at a young age or entering the workforce after school. \n\nWhen you're in your 20s, you may have fewer financial responsibilities, making it easier to save. You can start by setting realistic expectations and goals for your savings. It's important to have a clear understanding of your current and projected income, expenses, and how much you can afford to set aside for retirement. If you're unsure about retirement planning, it may be helpful to consult with a financial advisor who can help prioritize your goals and provide guidance.\n\nOne of the key benefits of starting to save early is compound interest. Compound interest is the interest earned on your initial savings and the reinvested earnings. Over time, compound interest can significantly increase the value of your savings. By starting early, you give your money more time to grow and benefit from compound interest. \n\nTo start saving, take advantage of employer-based retirement plans like a 401(k) or a Roth 401(k) if your employer offers them. These plans often come with employer matching contributions, which can boost your savings. Additionally, consider opening an individual retirement account (IRA) to further grow your savings. It's important to choose the right savings plan or scheme based on your financial needs and goals.\n\nRemember, the amount you save will depend on your individual circumstances, but even saving a small amount is better than not saving at all. The key is to get started and make saving a habit. By starting early and being consistent with your savings, you can set yourself up for a secure and comfortable future.",
      "name": "The best time to Start Saving",
      "stepItems": [],
      "uuid": "c8e23cd9-8eb6-4307-ade1-4c1029a6ee83"
    },
    {
      "content": "",
      "name": "Evaluation",
      "stepItems": [
        {
          "answerKeys": [
            "C"
          ],
          "choices": [
            {
              "content": "The interest earned on your initial savings only",
              "key": "A"
            },
            {
              "content": "The interest earned on your reinvested earnings only",
              "key": "B"
            },
            {
              "content": "The interest earned on your initial savings and the reinvested earnings",
              "key": "C"
            },
            {
              "content": "The interest earned on loans and debts",
              "key": "D"
            }
          ],
          "content": "What is compound interest?",
          "type": "SingleChoice",
          "uuid": "82b8158d-87b7-4539-bd0b-fff0cfc51404"
        },
        {
          "answerKeys": [
            "A"
          ],
          "choices": [
            {
              "content": "Your money has more time to grow and benefit from compound interest",
              "key": "A"
            },
            {
              "content": "You will have more financial responsibilities",
              "key": "B"
            },
            {
              "content": "You will have more money to spend on immediate needs",
              "key": "C"
            },
            {
              "content": "You can retire earlier",
              "key": "D"
            }
          ],
          "content": "What is the benefit of starting to save early?",
          "type": "SingleChoice",
          "uuid": "10b26206-c98d-4ab9-8e83-44c31afd9049"
        }
      ],
      "uuid": "1fa4b4a2-cead-4ebc-9aaa-2ce82b688e77"
    },
    {
      "content": "Saving money as a student can be challenging, but it is definitely possible with some smart strategies. One way to save money is by practicing financial management. Take the time to calculate your budget and evaluate your income and expenses. This will give you a clear picture of your financial status and help you make better decisions about your spending. It's also important to take advantage of your student status. Many businesses offer discounts and special deals for students, so be sure to ask about any student discounts whenever you can.\n\nAnother way to save money is by making use of free online services. Instead of always relying on paid software and subscriptions, look for free alternatives. For example, there are free online versions of popular software like Microsoft Office that can save you money. You can also take advantage of trial periods offered by entertainment providers like Netflix and Spotify. Additionally, consider practicing your cooking skills. Instead of spending money on expensive meals, try preparing your own food. You might be surprised at how much money you can save by cooking at home.\n\nIt's also important to reconsider your sports activities. While your university gym may offer a variety of sports activities, the membership fees can be expensive. Instead, consider alternative activities that don't require special equipment or memberships. Sports like basketball, football, or table tennis can be played for free, or you can try activities like yoga that you can do at home. Another tip for saving money is to think twice before shopping. Keep track of sales and exclusive deals, and make a list of items you need before making a purchase. Patience can pay off, as items often go on sale during holidays or seasonal transitions.\n\nLastly, be open to free stuff. Many businesses offer free products or giveaways specifically targeted at students. Take advantage of these opportunities and don't miss out on freebies that can help you save money. Additionally, consider sharing expenses with your friends. Splitting costs for things like cable TV or internet can help you save money while still enjoying the services you need. And finally, try the old-fashioned method of saving a penny a day. By gradually increasing the amount you save each day, you can accumulate a significant amount of money over time. Saving money as a student requires discipline and smart choices, but with these strategies, you can start building a solid financial foundation for your future.",
      "name": "Saving Money as a Student",
      "stepItems": [],
      "uuid": "354ead97-e871-46c7-9e2d-6ddbb82de18f"
    },
    {
      "content": "",
      "name": "Evaluation",
      "stepItems": [
        {
          "answerKeys": [
            "A"
          ],
          "choices": [
            {
              "content": "Something that is owned by a person or company and increases in value over time",
              "key": "A"
            },
            {
              "content": "Something that you buy from a shop",
              "key": "B"
            },
            {
              "content": "Something that decreases in value over time",
              "key": "C"
            },
            {
              "content": "Something that you buy for fun",
              "key": "D"
            }
          ],
          "content": "What is an asset?",
          "type": "SingleChoice",
          "uuid": "686bbce0-37b9-475b-9c1c-7a0ddb638b82"
        },
        {
          "answerKeys": [
            "B"
          ],
          "choices": [
            {
              "content": "By increasing the amount of money saved each day",
              "key": "A"
            },
            {
              "content": "By splitting costs for things like cable TV or internet",
              "key": "B"
            },
            {
              "content": "By buying expensive products or services",
              "key": "C"
            },
            {
              "content": "By avoiding free products or giveaways",
              "key": "D"
            }
          ],
          "content": "How can sharing expenses with friends help in saving money as a student?",
          "type": "SingleChoice",
          "uuid": "229af149-ffe8-409b-a106-254ea0982ca5"
        }
      ],
      "uuid": "2fa8b06c-d1b5-4446-8398-a005da1fe1bf"
    },
    {
      "content": "Investing strategies for Gen Z can be approached in a variety of ways. One important strategy is to start saving and investing as early as possible. By starting young, Gen Z individuals can take advantage of compound interest, which allows their money to grow over time. This means that even small amounts of savings can accumulate and generate significant returns in the long run.\n\nAnother strategy is to set specific investment goals. This includes both short-term and long-term goals. Short-term goals can be things like saving a certain amount of money within a year, while long-term goals can be focused on retirement planning. Setting these goals helps to provide direction and motivation for saving and investing.\n\nWhen it comes to investing, Gen Z individuals can consider various options. Employer-based retirement plans like a 401(k) or a Roth 401(k) can be a good starting point, especially if there is an employer match. Opening an individual retirement account (IRA) is another option to further grow savings. It's important to choose the right investment plan based on individual financial needs and goals.\n\nFor Gen Z students, saving money can be challenging, but there are strategies that can help. Practicing financial management by creating a budget and evaluating income and expenses is crucial. Taking advantage of student discounts and free online services can also help save money. Reconsidering sports activities and being mindful of shopping habits can contribute to saving as well. Lastly, being open to freebies and sharing expenses with friends can help stretch the budget.\n\nOverall, the key to investing strategies for Gen Z is to start early, set goals, and choose the right investment options based on individual circumstances. By being proactive and consistent with saving and investing, Gen Z individuals can build a solid financial foundation for their future.",
      "name": "Investing Strategies for Gen-Z",
      "stepItems": [],
      "uuid": "068605b9-07cf-4af3-9660-69bef09ceb17"
    },
    {
      "content": "",
      "name": "Evaluation",
      "stepItems": [
        {
          "answerKeys": [
            "A"
          ],
          "choices": [
            {
              "content": "Interest calculated on the initial principal and also on the accumulated interest of previous periods",
              "key": "A"
            },
            {
              "content": "Interest calculated only on the initial principal",
              "key": "B"
            },
            {
              "content": "Interest calculated only on the accumulated interest of previous periods",
              "key": "C"
            },
            {
              "content": "Interest calculated based on the current market rates",
              "key": "D"
            }
          ],
          "content": "What is compound interest?",
          "type": "SingleChoice",
          "uuid": "2ee6fb0e-552c-4c08-8f6b-e6664e35591e"
        },
        {
          "answerKeys": [
            "B"
          ],
          "choices": [
            {
              "content": "An investment account that provides tax advantages for retirement savings",
              "key": "A"
            },
            {
              "content": "An account for daily expenses and transactions",
              "key": "B"
            },
            {
              "content": "An account for short-term financial goals",
              "key": "C"
            },
            {
              "content": "An account for educational expenses",
              "key": "D"
            }
          ],
          "content": "What is an individual retirement account (IRA)?",
          "type": "SingleChoice",
          "uuid": "ebb995a7-b609-46da-8da4-261f07acd1f8"
        }
      ],
      "uuid": "8c501fab-9d9c-4035-9f7b-e63b75dc58c8"
    },
    {
      "content": "Choosing the best bank for your needs is an important decision that can have a significant impact on your financial well-being. There are several factors to consider when making this decision. \n\nFirst, you need to determine the type of bank that is right for you. There are traditional brick-and-mortar banks, online banks, and credit unions. Traditional banks offer a wide range of services and have physical branches where you can go for in-person assistance. Online banks, on the other hand, operate entirely online and often offer lower fees and higher interest rates. Credit unions are member-owned and can offer personalized service and community-focused benefits. \n\nNext, you should consider the fees and interest rates offered by different banks. Look for a bank that charges low fees for services like ATM withdrawals, account maintenance, and wire transfers. Additionally, compare the interest rates offered on savings accounts to ensure that you can earn the highest possible return on your money. \n\nIt's also important to consider the additional features and services offered by different banks. This could include things like online and mobile banking options, access to a network of ATMs, and security measures to protect your account. Think about your specific needs and preferences to determine which features are most important to you. \n\nLastly, it's crucial to choose a bank that you trust. Look for a bank with a solid reputation and positive customer reviews. Consider factors like the bank's longevity, financial stability, and customer service track record. Peace of mind is a crucial aspect of banking, so make sure you feel confident in the bank's ability to handle your money responsibly. \n\nRemember, choosing the best bank is not a one-time decision. Your needs and circumstances may change over time, so it's important to regularly evaluate your banking options and make changes if necessary. By considering factors like the type of bank, fees and interest rates, additional features, and trustworthiness, you can make an informed decision and choose the best bank for your needs.",
      "name": "Choosing the best bank ",
      "stepItems": [],
      "uuid": "2b859c72-a0c7-4ddf-a94b-0324c6e36142"
    },
    {
      "content": "",
      "name": "Evaluation",
      "stepItems": [
        {
          "answerKeys": [
            "A"
          ],
          "choices": [
            {
              "content": "Trust is important for peace of mind and confidence in the bank's ability to handle money responsibly",
              "key": "A"
            },
            {
              "content": "Trust is important for accessing online and mobile banking options",
              "key": "B"
            },
            {
              "content": "Trust is important for earning the highest possible return on your money",
              "key": "C"
            },
            {
              "content": "Trust is important for personalized service and community-focused benefits",
              "key": "D"
            }
          ],
          "content": "Why is it important to choose a bank that you trust?",
          "type": "SingleChoice",
          "uuid": "0be7d359-a36a-4ec2-8027-3251f7d87af1"
        },
        {
          "answerKeys": [
            "B"
          ],
          "choices": [
            {
              "content": "They have physical branches for in-person assistance",
              "key": "A"
            },
            {
              "content": "They offer lower fees and higher interest rates",
              "key": "B"
            },
            {
              "content": "They are member-owned and offer personalized service",
              "key": "C"
            },
            {
              "content": "They provide a wide range of services",
              "key": "D"
            }
          ],
          "content": "What is an advantage of online banks?",
          "type": "SingleChoice",
          "uuid": "0012c4df-46de-4024-9788-b983d7665abd"
        }
      ],
      "uuid": "5fbcf3da-7072-4c86-b43f-838d7f6b1fe8"
    }
  ],
  "thumbnail": "https://d31h13bdjwgzxs.cloudfront.net/academy/credit-union-academy/Guide/how_to_start_saving_credit_union_academy/1687942159419_how_to_start_saving.png",
  "uuid": "how-to-start-saving-credit-union-academy",
  "version": 1
}